pydiffuser/__init__.py
pydiffuser/_version.py
pydiffuser/exceptions.py
pydiffuser/logger.py
pydiffuser/typing.py
pydiffuser/_cli/__init__.py
pydiffuser/_cli/cli.py
pydiffuser/_cli/cli_utils.py
pydiffuser/mech/__init__.py
pydiffuser/mech/constants.py
pydiffuser/mech/fields.py
pydiffuser/models/__init__.py
pydiffuser/models/abp.py
pydiffuser/models/aoup.py
pydiffuser/models/bm.py
pydiffuser/models/levy.py
pydiffuser/models/mips.py
pydiffuser/models/rtp.py
pydiffuser/models/smoluchowski.py
pydiffuser/models/vicsek.py
pydiffuser/models/core/__init__.py
pydiffuser/models/core/base.py
pydiffuser/models/core/ctrw.py
pydiffuser/models/core/sde.py
pydiffuser/tracer/__init__.py
pydiffuser/tracer/component.py
pydiffuser/tracer/ensemble.py
pydiffuser/tracer/trajectory.py
pydiffuser/utils/__init__.py
pydiffuser/utils/config.py
pydiffuser/utils/helpers.py
pydiffuser/utils/jitted.py
pydiffuser/utils/random.py
pydiffuser/utils/utils.py
pydiffuser-0.0.3.dist-info/entry_points.txt
pydiffuser-0.0.3.dist-info/LICENSE
pydiffuser-0.0.3.dist-info/WHEEL
pydiffuser-0.0.3.dist-info/METADATA
pydiffuser-0.0.3.dist-info/RECORD
