Metadata-Version: 2.1
Name: pydiffuser
Version: 0.0.3
Summary: A simulation framework for nonequilibrium statistical physics
Keywords: nonequilibrium statistical physics,langevin dynamics,stochastic process,computer simulation
Author: Yurim Jung
Author-email: jung65537@gmail.com
Requires-Python: >=3.10
Classifier: Development Status :: 3 - Alpha
Classifier: Programming Language :: Python :: 3
Classifier: Intended Audience :: Developers
Classifier: Intended Audience :: Science/Research
Classifier: License :: OSI Approved :: Apache Software License
Classifier: Operating System :: OS Independent
Classifier: Programming Language :: Python :: 3.10
Classifier: Programming Language :: Python :: 3.11
Classifier: Programming Language :: Python :: 3.12
Classifier: Topic :: Scientific/Engineering
Classifier: Topic :: Scientific/Engineering :: Physics
Requires-Dist: jax>=0.4.18
Requires-Dist: jaxlib>=0.4.18
Project-URL: Homepage, https://github.com/jung235
Project-URL: Source, https://github.com/jung235/pydiffuser
